lampip/__init__.py
lampip/core/__init__.py
lampip/core/cloudformation.py
lampip/core/config.py
lampip/core/package.py
lampip/core/workspace.py
lampip/entrypoint.py
lampip-0.3.0.dist-info/WHEEL
lampip-0.3.0.dist-info/LICENSE
lampip-0.3.0.dist-info/METADATA
lampip-0.3.0.dist-info/entry_points.txt
lampip-0.3.0.dist-info/RECORD
